abrain.libs/libgcc_s-a3a07607.so.1
abrain.libs/libstdc++-496613c0.so.6.0.32
abrain/__init__.py
abrain/_cpp.cpython-310-x86_64-linux-gnu.so
abrain/_cpp/phenotype.pyi
abrain/_cpp/innovations.h
abrain/_cpp/misc.pyi
abrain/_cpp/genotype.pyi
abrain/_cpp/config.h
abrain/_cpp/config.cpp
abrain/_cpp/config.pyi
abrain/_cpp/__init__.pyi
abrain/_cpp/innovations.cpp
abrain/_cpp/genotype.h
abrain/_cpp/misc/point.hpp
abrain/_cpp/misc/utils.hpp
abrain/_cpp/phenotype/ann.cpp
abrain/_cpp/phenotype/eshn.cpp
abrain/_cpp/phenotype/cppn.cpp
abrain/_cpp/phenotype/ann.h
abrain/_cpp/phenotype/cppn.h
abrain/_cpp/phenotype/eshn.h
abrain/_bindings/utils.hpp
abrain/_bindings/config.cpp
abrain/_bindings/module.cpp
abrain/_bindings/innovations.cpp
abrain/_bindings/genotype.cpp
abrain/_bindings/phenotype/ann.cpp
abrain/_bindings/phenotype/cppn.cpp
abrain/core/config.py
abrain/core/ann.py
abrain/core/genome.py
abrain/core/cppn.py
abrain/core/functions/sin.png
abrain/core/functions/abs.png
abrain/core/functions/sin.svg
abrain/core/functions/id.svg
abrain/core/functions/gaus.svg
abrain/core/functions/bsgm.svg
abrain/core/functions/step.png
abrain/core/functions/plotter.sh
abrain/core/functions/abs.svg
abrain/core/functions/ssgm.png
abrain/core/functions/step.svg
abrain/core/functions/gaus.png
abrain/core/functions/ssgm.svg
abrain/core/functions/template.tex
abrain/core/functions/ssgn.svg
abrain/core/functions/bsgm.png
abrain/core/functions/ssgn.png
abrain/core/functions/id.png
abrain-1.0rc0.post7.dist-info/WHEEL
abrain-1.0rc0.post7.dist-info/LICENSE
abrain-1.0rc0.post7.dist-info/top_level.txt
abrain-1.0rc0.post7.dist-info/RECORD
abrain-1.0rc0.post7.dist-info/METADATA
