Metadata-Version: 2.1
Name: abrain
Version: 1.0rc0.post7
Summary: NeuroEvolution in Python backed by C++ computations
Author-email: Kevin Godin-Dubois <k.j.m.godin-dubois@vu.nl>
Project-URL: Homepage, https://github.com/kgd-al/abrain
Project-URL: Documentation, https://abrain.rtfd.io
Project-URL: Bug Tracker, https://github.com/kgd-al/abrain/issues
Classifier: Development Status :: 3 - Alpha
Classifier: Programming Language :: C++
Classifier: Programming Language :: Python :: 3 :: Only
Classifier: Programming Language :: Python :: 3.8
Classifier: License :: OSI Approved :: MIT License
Classifier: Operating System :: Unix
Classifier: Intended Audience :: Science/Research
Classifier: Topic :: Scientific/Engineering :: Artificial Intelligence
Classifier: Topic :: Scientific/Engineering :: Artificial Life
Requires-Python: >=3.8
License-File: LICENSE
Requires-Dist: plotly
Requires-Dist: importlib-resources
Requires-Dist: graphviz
Requires-Dist: pyrecord
Provides-Extra: all-tests
Requires-Dist: abrain[kaleido,tests] ; extra == 'all-tests'
Requires-Dist: leap-ec ; extra == 'all-tests'
Requires-Dist: Pillow ; extra == 'all-tests'
Requires-Dist: qdpy ; extra == 'all-tests'
Requires-Dist: tqdm ; extra == 'all-tests'
Requires-Dist: matplotlib ; extra == 'all-tests'
Provides-Extra: docs
Requires-Dist: sphinx ; extra == 'docs'
Requires-Dist: sphinx-pyproject ; extra == 'docs'
Requires-Dist: sphinx-design ; extra == 'docs'
Requires-Dist: sphinx-tabs ; extra == 'docs'
Requires-Dist: matplotlib ; extra == 'docs'
Requires-Dist: sphinx-copybutton ; extra == 'docs'
Requires-Dist: myst-parser ; extra == 'docs'
Requires-Dist: furo ; extra == 'docs'
Provides-Extra: kaleido
Requires-Dist: kaleido ; extra == 'kaleido'
Provides-Extra: tests
Requires-Dist: pytest ; extra == 'tests'
Requires-Dist: pytest-steps ; extra == 'tests'
Requires-Dist: pytest-sugar ; extra == 'tests'
Requires-Dist: coverage ; extra == 'tests'
Requires-Dist: flake8 ; extra == 'tests'
